{
  "project_info": {
    "project_number": "678889617866",
    "project_id": "simulator-matches",
    "storage_bucket": "simulator-matches.appspot.com"
  },
  "client": [
    {
      "client_info": {
        "mobilesdk_app_id": "1:678889617866:android:84fd58e6f8ea6aaf7df733",
        "android_client_info": {
          "package_name": "com.example.appsimulator"
        }
      },
      "oauth_client": [
        {
          "client_id": "678889617866-06verhfdjo7s82hn93ca5oh0kk1vgms2.apps.googleusercontent.com",
          "client_type": 3
        }
      ],
      "api_key": [
        {
          "current_key": "AIzaSyBHThG9R_Prw02TwUfaMg5_XmxxPRYTK18"
        }
      ],
      "services": {
        "appinvite_service": {
          "other_platform_oauth_client": [
            {
              "client_id": "678889617866-06verhfdjo7s82hn93ca5oh0kk1vgms2.apps.googleusercontent.com",
              "client_type": 3
            }
          ]
        }
      }
    }
  ],
  "configuration_version": "1"
}